bilibili.py
netmind_bilibili_mcp_server-0.1.2.dist-info/licenses/LICENSE
netmind_bilibili_mcp_server-0.1.2.dist-info/METADATA
netmind_bilibili_mcp_server-0.1.2.dist-info/WHEEL
netmind_bilibili_mcp_server-0.1.2.dist-info/entry_points.txt
netmind_bilibili_mcp_server-0.1.2.dist-info/top_level.txt
netmind_bilibili_mcp_server-0.1.2.dist-info/RECORD
